pythonuef_github_lib_template/__init__.py
pythonuef_github_lib_template-0.1.0.dist-info/licenses/LICENSE
tests/test_country.py
pythonuef_github_lib_template-0.1.0.dist-info/METADATA
pythonuef_github_lib_template-0.1.0.dist-info/WHEEL
pythonuef_github_lib_template-0.1.0.dist-info/top_level.txt
pythonuef_github_lib_template-0.1.0.dist-info/RECORD
