Metadata-Version: 2.4
Name: pythonuef-github-lib-template
Version: 0.1.0
Summary: github lib template
Author: pythonuef
License: MIT
License-File: LICENSE
Dynamic: license-file
